docsend2pdf/__init__.py
docsend2pdf/client.py
docsend2pdf/exceptions.py
docsend2pdf-0.0.1.dist-info/LICENSE
docsend2pdf-0.0.1.dist-info/METADATA
docsend2pdf-0.0.1.dist-info/WHEEL
docsend2pdf-0.0.1.dist-info/top_level.txt
docsend2pdf-0.0.1.dist-info/RECORD
