Metadata-Version: 2.2
Name: docsend2pdf
Version: 0.0.1
Summary: Python wrapper for DocSend2PDF
Home-page: https://github.com/samuel-poon/docsend2pdf-py
Requires-Python: >=3.8
License-File: LICENSE
Requires-Dist: requests
Requires-Dist: beautifulsoup4
Dynamic: description
Dynamic: description-content-type
Dynamic: home-page
Dynamic: requires-dist
Dynamic: requires-python
Dynamic: summary
